{
  "data": {
    "applicationsByProgramV2": {
      "data": [
        {
          "id": "1",
          "applicantId": "2",
          "status": "accepted",
          "content": "I am a great candidate for this program.",
          "picked": true,
          "createdAt": "2024-01-20T12:00:00.000Z",
          "applicant": {
            "id": "2",
            "firstName": "John",
            "lastName": "Doe",
            "email": "john@example.com"
          }
        },
        {
          "id": "3",
          "applicantId": "5",
          "status": "applied",
          "content": "Another application content",
          "picked": false,
          "createdAt": "2024-01-21T10:00:00.000Z",
          "applicant": {
            "id": "5",
            "firstName": "Jane",
            "lastName": "Smith",
            "email": "jane@example.com"
          }
        }
      ],
      "count": 2,
      "totalPages": 1,
      "currentPage": 1,
      "hasNextPage": false,
      "hasPreviousPage": false
    }
  }
}

